setup.cfg
setup.py
my_project/__init__.py
my_project.egg-info/PKG-INFO
my_project.egg-info/SOURCES.txt
my_project.egg-info/dependency_links.txt
my_project.egg-info/entry_points.txt
my_project.egg-info/not-zip-safe
my_project.egg-info/requires.txt
my_project.egg-info/top_level.txt