Metadata-Version: 1.0
Name: my-project
Version: 0.1dev
Summary: Esta es la descripcion breve
Home-page: http://google.com
Author: Franco Pellegrini
Author-email: frapell@gmail.com
License: GPL2
Keywords: package test muestra
Platform: UNKNOWN
